Metadata-Version: 1.0
Name: rim-prob-dist
Version: 0.1
Summary: Gaussian and Binomial distributions
Home-page: UNKNOWN
Author: Andres Iglesias
Author-email: amir_andres@hotmail.com
License: UNKNOWN
Platform: UNKNOWN
